MutPy_Pynguin-0.7.1.data/scripts/mut.py
mutpy/__init__.py
mutpy/codegen.py
mutpy/commandline.py
mutpy/controller.py
mutpy/coverage.py
mutpy/termcolor.py
mutpy/utils.py
mutpy/views.py
mutpy/operators/__init__.py
mutpy/operators/arithmetic.py
mutpy/operators/base.py
mutpy/operators/decorator.py
mutpy/operators/exception.py
mutpy/operators/inheritance.py
mutpy/operators/logical.py
mutpy/operators/loop.py
mutpy/operators/misc.py
mutpy/templates/base.html
mutpy/templates/detail.html
mutpy/templates/index.html
mutpy/test_runners/__init__.py
mutpy/test_runners/base.py
mutpy/test_runners/pytest_runner.py
mutpy/test_runners/unittest_runner.py
MutPy_Pynguin-0.7.1.dist-info/LICENSE
MutPy_Pynguin-0.7.1.dist-info/METADATA
MutPy_Pynguin-0.7.1.dist-info/WHEEL
MutPy_Pynguin-0.7.1.dist-info/top_level.txt
MutPy_Pynguin-0.7.1.dist-info/RECORD
