Metadata-Version: 2.1
Name: MutPy-Pynguin
Version: 0.7.1
Summary: Mutation testing tool for Python 3.x source code.
Home-page: https://github.com/se2p/mutpy-pynguin
Author: Konrad Hałas
Author-email: halas.konrad@gmail.com
Maintainer: Stephan Lukasczyk
Maintainer-email: stephan.lukasczyk@uni-passau.de
License: UNKNOWN
Download-URL: https://github.com/se2p/mutpy-pynguin
Platform: UNKNOWN
Classifier: Programming Language :: Python :: 3.8
Classifier: Programming Language :: Python :: 3.9
Classifier: Environment :: Console
Classifier: Intended Audience :: Developers
Classifier: Topic :: Software Development :: Testing
Classifier: License :: OSI Approved :: Apache Software License
Requires-Python: >=3.8
Provides-Extra: pytest
License-File: LICENSE
